datepy/__init__.py
datepy/datepy.py
datepy-0.2.0.dist-info/LICENSE
datepy-0.2.0.dist-info/METADATA
datepy-0.2.0.dist-info/WHEEL
datepy-0.2.0.dist-info/top_level.txt
datepy-0.2.0.dist-info/RECORD
