Metadata-Version: 2.1
Name: datepy
Version: 0.2.0
Summary: A robust utility for parsing dates in various formats.
Author: msj121
License-File: LICENSE
Requires-Dist: dateparser
